neglect.py
neglect-0.1.9.dist-info/LICENSE
neglect-0.1.9.dist-info/METADATA
neglect-0.1.9.dist-info/WHEEL
neglect-0.1.9.dist-info/top_level.txt
neglect-0.1.9.dist-info/RECORD
