Metadata-Version: 2.1
Name: neglect
Version: 0.1.9
Summary: Neglecting usage of Exceptional handling in Python
Author: Vishal R
Keywords: neglect,NEGLECT,neglect try except,ignore,omit,neglect exceptional handling
Classifier: Programming Language :: Python :: 3
Classifier: License :: OSI Approved :: MIT License
Classifier: Operating System :: OS Independent
Requires-Python: >=3.6
License-File: LICENSE
